seqreg/__init__.py
seqreg/poolboiling.py
seqreg/seqreg.py
seqreg/Models/Hit2Flux.json
seqreg/Models/imgreg.json
seqreg/Models/models.json
seqreg-0.0.11.dist-info/LICENSE.txt
seqreg-0.0.11.dist-info/METADATA
seqreg-0.0.11.dist-info/WHEEL
seqreg-0.0.11.dist-info/top_level.txt
seqreg-0.0.11.dist-info/RECORD
