Metadata-Version: 2.1
Name: seqreg
Version: 0.0.11
Summary: Sequence Regression Functions
Home-page: https://github.com/cldunlap73/SeqReg
Author: cldunlap
Author-email: christydunlap26@gmail.com
License: Apache-2.0
Classifier: License :: OSI Approved :: Apache Software License
License-File: LICENSE.txt
